{
      "random_first": 0,
      "random_second": 3,
      "random_third": 19,
      "random_fourth": 28,
      "random_fifth": 44,
      "random_sixth": 79,
      "gold_first": 86,
      "gold_second": 45,
      "gold_third": 31,
      "gold_fourth": 7,
      "gold_fifth": 3,
      "gold_sixth": 1,
      "baseline_first": 10,
      "baseline_second": 40,
      "baseline_third": 34,
      "baseline_fourth": 48,
      "baseline_fifth": 37,
      "baseline_sixth": 4,
      "neural25_first": 23,
      "neural25_second": 30,
      "neural25_third": 29,
      "neural25_fourth": 31,
      "neural25_fifth": 32,
      "neural25_sixth": 28,
      "neural50_first": 26,
      "neural50_second": 31,
      "neural50_third": 31,
      "neural50_fourth": 35,
      "neural50_fifth": 30,
      "neural50_sixth": 20,
      "snh_first": 28,
      "snh_second": 24,
      "snh_third": 29,
      "snh_fourth": 24,
      "snh_fifth": 27,
      "snh_sixth": 41
}